[
  {
    "id": "1",
    "name": "Sophia Lee",
    "profileImage": "https://i.ibb.co.com/9p7N3RV/class-img-5.jpg",
     "expertise": ["Yoga", "Mindfulness", "Personal Training"],
    "experience": 5,
    "socialLinks": [
      { "platform": "facebook", "url": "https://facebook.com/sophia" },
      { "platform": "twitter", "url": "https://twitter.com/sophia" },
      { "platform": "linkedin", "url": "https://linkedin.com/in/sophia" }
    ],
    "availableSlots": "Monday - Friday, 9 AM to 5 PM"
  },
  {
    "id": "2",
    "name": "Michael Brown",
    "profileImage": "https://i.ibb.co.com/C6WNKPX/class-1-bg.jpg",
    "expertise": ["Strength Training", "Weightlifting", "Muscle Building"],
    "experience": 8,
    "socialLinks": [
      { "platform": "instagram", "url": "https://instagram.com/michael" },
      { "platform": "linkedin", "url": "https://linkedin.com/in/michael" }
    ],
    "availableSlots": "Weekends, 10 AM to 4 PM"
  },
  {
    "id": "3",
    "name": "Emma Davis",
    "profileImage": "https://i.ibb.co.com/Vx9HzCr/class-img-3.jpg",
     "expertise": ["Pilates", "Flexibility Training", "Posture Correction"],
    "experience": 3,
    "socialLinks": [
      { "platform": "facebook", "url": "https://facebook.com/emma" },
      { "platform": "twitter", "url": "https://twitter.com/emma" }
    ],
    "availableSlots": "Tuesday - Thursday, 1 PM to 7 PM"
  },
  {
    "id": "4",
    "name": "Oliver Martinez",
    "profileImage": "https://i.ibb.co.com/C6WNKPX/class-1-bg.jpg",
    "expertise": ["CrossFit", "HIIT", "Endurance Training"],
    "experience": 7,
    "socialLinks": [
      { "platform": "facebook", "url": "https://facebook.com/oliver" },
      { "platform": "instagram", "url": "https://instagram.com/oliver" },
      { "platform": "linkedin", "url": "https://linkedin.com/in/oliver" }
    ],
    "availableSlots": "Monday - Friday, 10 AM to 6 PM"
  },
  {
    "id": "5",
    "name": "Isabella Wilson",
    "profileImage": "https://i.ibb.co.com/VTz6W9Y/athlete-5.jpg",
    "expertise": ["Zumba", "Dance Fitness", "Cardio"],
    "experience": 4,
    "socialLinks": [
      { "platform": "twitter", "url": "https://twitter.com/isabella" },
      { "platform": "instagram", "url": "https://instagram.com/isabella" }
    ],
    "availableSlots": "Weekends, 9 AM to 3 PM"
  },
  {
    "id": "6",
    "name": "low Brown",
    "profileImage": "https://i.ibb.co.com/wyfTXQZ/pexels-olly-3775566.jpg",
    "expertise": ["Functional Fitness", "Weight Loss", "Personal Training"],
    "experience": 6,
    "socialLinks": [
      { "platform": "linkedin", "url": "https://linkedin.com/in/liam" },
      { "platform": "facebook", "url": "https://facebook.com/liam" }
    ],
    "availableSlots": "Monday - Thursday, 12 PM to 8 PM"
  }
  
]
